Assignment_4/Intro_to_Verilog/1to2_Demux.v
`timescale 1ns / 1ps

module two_demux(y,S,a,b);
input y,S;
output a,b;
and A1(a,~S,y);
and A2(b,S,y);
endmodule

module demux_four(y,S_0,S_1,a,b,c,d);
input y,S_0,S_1;
output a,b,c,d;
wire p,q;
two_demux B1(y,S_1,p,q);
two_demux B2(p,S_0,a,b);
two_demux B3(q,S_0,c,d);
endmodule

Assignment_4/Intro_to_Verilog/1to2_Demux_tb.v
`timescale 1ns / 1ps
module demux_four_test;

// Inputs
reg y;
reg S_0;
reg S_1;

// Outputs
wire a;
wire b;
wire c;
wire d;

// Instantiate the Unit Under Test (UUT)
demux_four uut (
    .y(y),
    .S_0(S_0),
    .S_1(S_1),
    .a(a),
    .b(b),
    .c(c),
    .d(d)
);

initial begin
    // Initialize Inputs
    $dumpfile("demux_four_test.vcd");
    $dumpvars(0,demux_four_test);
    y = 0;
    S_0 = 0;
    S_1 = 0;
    #100 $finish;
end

// Add stimulus here
always #20 y = ~y;
always #5 S_0 = ~S_0;
always #10 S_1 = ~S_1;
always@(y or S_0 or S_1)
    $monitor("time = %t \t y = %d, S1 = %d, S2 = %d, a = %d, b = %d, c = %d, d = %d",$time,y,S_1,S_0,a,b,c,d);

endmodule

Assignment_4/Intro_to_Verilog/demux_four_test.vcd
$date
	Thu Sep 11 04:00:06 2025
$end
$version
	Icarus Verilog
$end
$timescale
	1ps
$end
$scope module demux_four_test $end
$var wire 1 ! d $end
$var wire 1 " c $end
$var wire 1 # b $end
$var wire 1 $ a $end
$var reg 1 % S_0 $end
$var reg 1 & S_1 $end
$var reg 1 ' y $end
$scope module uut $end
$var wire 1 % S_0 $end
$var wire 1 & S_1 $end
$var wire 1 ' y $end
$var wire 1 ( q $end
$var wire 1 ) p $end
$var wire 1 ! d $end
$var wire 1 " c $end
$var wire 1 # b $end
$var wire 1 $ a $end
$scope module B1 $end
$var wire 1 & S $end
$var wire 1 ) a $end
$var wire 1 ( b $end
$var wire 1 ' y $end
$upscope $end
$scope module B2 $end
$var wire 1 % S $end
$var wire 1 $ a $end
$var wire 1 # b $end
$var wire 1 ) y $end
$upscope $end
$scope module B3 $end
$var wire 1 % S $end
$var wire 1 " a $end
$var wire 1 ! b $end
$var wire 1 ( y $end
$upscope $end
$upscope $end
$upscope $end
$enddefinitions $end
$comment Show the parameter values. $end
$dumpall
$end
#0
$dumpvars
0)
0(
0'
0&
0%
0$
0#
0"
0!
$end
#5000
1%
#10000
0%
1&
#15000
1%
#20000
1$
1)
0%
0&
1'
#25000
0$
1#
1%
#30000
0)
1"
0#
1(
0%
1&
#35000
0"
1!
1%
#40000
0!
0(
0%
0&
0'
#45000
1%
#50000
0%
1&
#55000
1%
#60000
1$
1)
0%
0&
1'
#65000
0$
1#
1%
#70000
0)
1"
0#
1(
0%
1&
#75000
0"
1!
1%
#80000
0!
0(
0%
0&
0'
#85000
1%
#90000
0%
1&
#95000
1%
#100000
1$
1)
0%
0&
1'
