Assignment_4/Intro_to_Verilog/dff.v
`timescale 1ns / 1ps
module dff(clk,rst,D,Q);
input clk,rst,D;
output reg Q;
always@(posedge clk or negedge rst)
begin
if(!rst)
Q <= 1'b0;
else
Q <= D;
end
endmodule

Assignment_4/Intro_to_Verilog/dff_tb.v
`timescale 1ns / 1ps
module dff_test;

// Inputs
reg clk;
reg rst;
reg D;

// Outputs
wire Q;

// Instantiate the Unit Under Test (UUT)
dff uut (
    .clk(clk),
    .rst(rst),
    .D(D),
    .Q(Q)
);

initial begin
    // Initialize Inputs
    $dumpfile("dff_test.vcd");
    $dumpvars(0,dff_test);
    clk = 1;
    rst = 0;
    D = 0;
    #100 $finish;
end

always #5 clk = ~clk;
always #20 rst = ~rst;
always #10 D = ~D;
always@(D or rst)
$monitor("time = %t \t rst = %b, clk = %d, D = %b, Q = %b",$time,rst,clk,D,Q);

endmodule

Assignment_4/Intro_to_Verilog/dff_test.vcd
$date
	Thu Sep 11 04:04:02 2025
$end
$version
	Icarus Verilog
$end
$timescale
	1ps
$end
$scope module dff_test $end
$var wire 1 ! Q $end
$var reg 1 " D $end
$var reg 1 # clk $end
$var reg 1 $ rst $end
$scope module uut $end
$var wire 1 " D $end
$var wire 1 # clk $end
$var wire 1 $ rst $end
$var reg 1 ! Q $end
$upscope $end
$upscope $end
$enddefinitions $end
$comment Show the parameter values. $end
$dumpall
$end
#0
$dumpvars
0$
1#
0"
0!
$end
#5000
0#
#10000
1#
1"
#15000
0#
#20000
1#
0"
1$
#25000
0#
#30000
1!
1#
1"
#35000
0#
#40000
0!
1#
0"
0$
#45000
0#
#50000
1#
1"
#55000
0#
#60000
1#
0"
1$
#65000
0#
#70000
1!
1#
1"
#75000
0#
#80000
0!
1#
0"
0$
#85000
0#
#90000
1#
1"
#95000
0#
#100000
1#
0"
1$
