Assignment_4/Intro_to_Verilog/1to2_decoder.v
`timescale 1ns / 1ps
module two_decoder(a,en,y1,y2);
input a,en;
output y1,y2;
and A1(y1,~a,en);
and A2(y2,a,en);
endmodule

Assignment_4/Intro_to_Verilog/1to2_Decoder_tb.v
`timescale 1ns / 1ps
module two_decoder_test;

// Inputs
reg a;
reg en;

// Outputs
wire y1;
wire y2;

// Instantiate the Unit Under Test (UUT)
two_decoder uut (
    .a(a),
    .en(en),
    .y1(y1),
    .y2(y2)
);

initial begin
    $dumpfile("two_decoder_test.vcd");
    $dumpvars(0,two_decoder_test);
    // Initialize Inputs
    a = 1'b0;
    en = 1'b0;
    #100 $finish;
end

always #5 a = ~a;
always #10 en = ~en;
always@(a)
$monitor("time = %t \t a = %b, en = %d, y1 = %d, y2 = %d",$time,a,en,y1,y2);

endmodule

Assignment_4/Intro_to_Verilog/two_decoder_test.vcd
$date
	Thu Sep 11 03:50:37 2025
$end
$version
	Icarus Verilog
$end
$timescale
	1ps
$end
$scope module two_decoder_test $end
$var wire 1 ! y2 $end
$var wire 1 " y1 $end
$var reg 1 # a $end
$var reg 1 $ en $end
$scope module uut $end
$var wire 1 # a $end
$var wire 1 $ en $end
$var wire 1 " y1 $end
$var wire 1 ! y2 $end
$upscope $end
$upscope $end
$enddefinitions $end
$comment Show the parameter values. $end
$dumpall
$end
#0
$dumpvars
0$
0#
0"
0!
$end
#5000
1#
#10000
1"
0#
1$
#15000
0"
1!
1#
#20000
0!
0#
0$
#25000
1#
#30000
1"
0#
1$
#35000
0"
1!
1#
#40000
0!
0#
0$
#45000
1#
#50000
1"
0#
1$
#55000
0"
1!
1#
#60000
0!
0#
0$
#65000
1#
#70000
1"
0#
1$
#75000
0"
1!
1#
#80000
0!
0#
0$
#85000
1#
#90000
1"
0#
1$
#95000
0"
1!
1#
#100000
0!
0#
0$
